miss_hit_core/__init__.py
miss_hit_core/cfg_ast.py
miss_hit_core/cfg_parser.py
miss_hit_core/cfg_tree.py
miss_hit_core/command_line.py
miss_hit_core/config.py
miss_hit_core/errors.py
miss_hit_core/m_ast.py
miss_hit_core/m_entity_root.py
miss_hit_core/m_language.py
miss_hit_core/m_language_builtins.py
miss_hit_core/m_lexer.py
miss_hit_core/m_parse_utils.py
miss_hit_core/m_parser.py
miss_hit_core/m_types.py
miss_hit_core/mh_metric.py
miss_hit_core/mh_style.py
miss_hit_core/pathutil.py
miss_hit_core/resources.py
miss_hit_core/s_ast.py
miss_hit_core/s_parser.py
miss_hit_core/version.py
miss_hit_core/work_package.py
miss_hit_core/resources/style.css
miss_hit_core/resources/assets/alert-triangle.svg
miss_hit_core/resources/assets/bar-chart-2.svg
miss_hit_core/resources/assets/check-square.svg
miss_hit_core/resources/assets/download.svg
miss_hit_core/resources/assets/edit.svg
miss_hit_core/resources/assets/external-link.svg
miss_hit_core/resources/assets/file-text.svg
miss_hit_core/resources/assets/help-circle.svg
miss_hit_core/resources/assets/package.svg
miss_hit_core/resources/assets/settings.svg
miss_hit_core/resources/assets/terminal.svg
miss_hit_core-0.9.44.dist-info/LICENSE
miss_hit_core-0.9.44.dist-info/LICENSE.AGPL
miss_hit_core-0.9.44.dist-info/METADATA
miss_hit_core-0.9.44.dist-info/WHEEL
miss_hit_core-0.9.44.dist-info/entry_points.txt
miss_hit_core-0.9.44.dist-info/top_level.txt
miss_hit_core-0.9.44.dist-info/RECORD
